spawny/__init__.py
spawny/_version.py
spawny/main.py
spawny/main_remotes_and_defs.py
spawny/py.typed
spawny/utils_logging.py
spawny/utils_object_proxy.py
spawny-2.1.4.dist-info/LICENSE
spawny-2.1.4.dist-info/METADATA
spawny-2.1.4.dist-info/WHEEL
spawny-2.1.4.dist-info/top_level.txt
spawny-2.1.4.dist-info/RECORD
