Metadata-Version: 2.1
Name: spawny
Version: 2.1.4
Summary: Spawns a pythyon script as a daemon in another process, possibly using another python executable/environment
Home-page: https://github.com/smarie/python-spawny
Maintainer: Sylvain MARIE
Maintainer-email: sylvain.marie@se.com
License: BSD 3-Clause
Download-URL: https://github.com/smarie/python-spawny/tarball/2.1.4
Keywords: spawn script object process daemon proxy rpc distribute
Platform: UNKNOWN
Classifier: Development Status :: 5 - Production/Stable
Classifier: Intended Audience :: Developers
Classifier: Topic :: Software Development :: Libraries :: Python Modules
Classifier: License :: OSI Approved :: BSD License
Classifier: Programming Language :: Python :: 2.7
Classifier: Programming Language :: Python :: 3.5
Classifier: Programming Language :: Python :: 3.6
Classifier: Programming Language :: Python :: 3.7
Obsoletes: pyoad
Requires-Dist: future ; python_version < "3.2"
